lab1/FIR_TAP64.sv
`timescale 1ns / 1ps

module FIR_TAP64(clk, rst, data_in, data_out);
//Parameter Declaration
parameter data_bits = 10; //Bit-width of inputs
parameter coeff_bits = 10; //Bit-width of coefficients
parameter dataout_bits = data_bits + coeff_bits; //Bit-width of output
parameter N = 63;
integer i;

//Input Signals Declaration
input clk;
input rst;
input logic [data_bits-1:0] data_in;
output logic [dataout_bits-1:0] data_out;

//Internal signal declaration
reg signed [coeff_bits-1:0] coeff[N-1:0];	//Coefficient register
reg signed [data_bits-1:0] shift_reg[N-1:0];	//Shift Register
reg signed [dataout_bits-1:0] product[N-1:0];	//Product Register
reg signed [dataout_bits-1:0] sum;		//Summation out
reg signed [data_bits-1:0] datain_buf;		//Input Buffer

assign data_out = sum;

//Load the coefficients into the signal
initial begin
	//Read the coeff from the .mem file
	$readmemb("coeff_bin.mem", coeff, 0, N-1);
    	//Testing
	// Display all coefficients
    	//$display("Printing all coefficients:");
    	//for(int i = 0; i < N; i = i + 1) begin
        	//$display("coeff[%0d] = %b", i, coeff[i]);
    	//end
	
end

//Logic for the input buffer
always_ff @(posedge clk)
begin
	if(rst) begin
		for (i = 0; i < N; i = i + 1) begin
                	shift_reg[i] = 0;
                	product[i] = 0;
		end
		sum <= 0;
		datain_buf <= 0;	
	end
	else begin
		//Inputing the data and shifting the register
		datain_buf <= data_in;
		for (i = N - 1; i > 0; i = i - 1) begin
			shift_reg[i] <= shift_reg[i - 1];
		end
		shift_reg[0] <= datain_buf;
		
		//Multiplying
		for(i = 0; i < N; i = i + 1) begin
			product[i] = shift_reg[i] * coeff[i];
		end

		//Compute sum
		sum = 0;
		for(int i = 0; i < N; i = i + 1) begin
			sum = sum + product[i];
		end
			
	end
end

endmodule;

lab1/tb.sv
module fir_tb;

//Parameter Declaration
parameter data_bits = 10; //Bit-width of inputs
parameter coeff_bits = 10; //Bit-width of coefficients
parameter dataout_bits = data_bits + coeff_bits; //Bit-width of output
parameter N = 63;
integer i;
parameter N_input = 2000;
integer file;
integer count = 0;

//Input Signals Declaration
reg clk;
reg rst;
reg signed [data_bits-1:0] data_in;
wire signed [dataout_bits-1:0] data_out;

//400 Hz signal geeration
reg [31:0] counter_400hz; // Counter for 400 Hz signal
reg [31:0] counter_500hz; // Counter for 500 Hz signal
reg signed [data_bits-1:0] signal_400hz; // 400 Hz signal
reg signed [data_bits-1:0] signal_500hz; // 500 Hz signal

//Internal Signal declartion
reg signed [data_bits-1:0] mem[N_input-1:0];

//Wiring the unit test
FIR_TAP64 U1(	.clk(clk), 
		.rst(rst), 
		.data_in(data_in), 
		.data_out(data_out)
);
// Clock generation
always begin
        clk = 1; #250;
       	clk = 0; #250;	// 2kHz clock (500ns period -> 2kHz)
end

//Test procedure
initial begin 
	clk = 0;
	rst = 1;
	data_in = 0;
	$readmemb("in_bin.mem", mem, 0, N_input-1);
	
	#500;
	//Release Reset
	rst = 0;
	#500;
	//Input procedure
	for(i = 0 ; i < N_input-1 ; i = i+1) begin
		data_in = mem[i];
		$fwrite(file, "%b\n", data_out);
		#500;
	end
	// End simulation
	$finish;
end

initial begin
	$dumpfile("tb.vcd");
        $dumpvars;
	file = $fopen("sim.out", "w");
end

endmodule;

lab1/tb.vcd
$date
	Mon Oct  2 17:21:43 2023
$end
$version
	Icarus Verilog
$end
$timescale
	1ps
$end
$scope module fir_tb $end
$var wire 20 ! data_out [19:0] $end
$var parameter 32 " N $end
$var parameter 32 # N_input $end
$var parameter 32 $ coeff_bits $end
$var parameter 32 % data_bits $end
$var parameter 33 & dataout_bits $end
$var reg 1 ' clk $end
$var reg 10 ( data_in [9:0] $end
$var reg 1 ) rst $end
$var integer 32 * count [31:0] $end
$var integer 32 + file [31:0] $end
$var integer 32 , i [31:0] $end
$scope module U1 $end
$var wire 1 ' clk $end
$var wire 10 - data_in [9:0] $end
$var wire 20 . data_out [19:0] $end
$var wire 1 ) rst $end
$var parameter 32 / N $end
$var parameter 32 0 coeff_bits $end
$var parameter 32 1 data_bits $end
$var parameter 33 2 dataout_bits $end
$var reg 10 3 datain_buf [9:0] $end
$var reg 20 4 sum [19:0] $end
$var integer 32 5 i [31:0] $end
$scope begin $ivl_for_loop0 $end
$var integer 32 6 i [31:0] $end
$upscope $end
$upscope $end
$upscope $end
$enddefinitions $end
$comment Show the parameter values. $end
$dumpall
b10100 2
b1010 1
b1010 0
b111111 /
b10100 &
b1010 %
b1010 $
b11111010000 #
b111111 "
$end
#0
$dumpvars
b0 6
b111111 5
b0 4
b0 3
b0 .
b0 -
bx ,
b10000000000000000000000000000011 +
b0 *
1)
b0 (
0'
b0 !
$end
#500000
b111111 6
b111111 5
1'
0)
#750000
0'
#1000000
b111111 6
b111111 5
1'
b0 ,
#1250000
0'
#1500000
b111110011 3
b111111 6
b111111 5
1'
b111110011 (
b111110011 -
b1 ,
#1750000
0'
#2000000
b10010101 3
b111111 6
b111111 5
1'
b10010101 (
b10010101 -
b10 ,
#2250000
0'
#2500000
b1001101010 3
b111111 6
b111111 5
1'
b1001101010 (
b1001101010 -
b11 ,
#2750000
0'
#3000000
b1100001110 3
b111111 6
b111111 5
1'
b1100001110 (
b1100001110 -
b100 ,
#3250000
0'
#3500000
b100000000 3
b11111111111000001101 !
b11111111111000001101 .
b11111111111000001101 4
b111111 6
b111111 5
1'
b100000000 (
b100000000 -
b101 ,
#3750000
0'
#4000000
b11110010 3
b111111 6
b11111111101110000101 !
b11111111101110000101 .
b11111111101110000101 4
b111111 5
1'
b11110010 (
b11110010 -
b110 ,
#4250000
0'
#4500000
b1110010110 3
b111111 6
b11111111111001111001 !
b11111111111001111001 .
b11111111111001111001 4
b111111 5
1'
b1110010110 (
b1110010110 -
b111 ,
#4750000
0'
#5000000
b1101101011 3
b111111 6
b1110001001 !
b1110001001 .
b1110001001 4
b111111 5
1'
b1101101011 (
b1101101011 -
b1000 ,
#5250000
0'
#5500000
b1100 3
b111111 6
b10001101101 !
b10001101101 .
b10001101101 4
b111111 5
1'
b1100 (
b1100 -
b1001 ,
#5750000
0'
#6000000
b0 3
b111111 6
b11111111111010010101 !
b11111111111010010101 .
b11111111111010010101 4
b111111 5
1'
b0 (
b0 -
b1010 ,
#6250000
0'
#6500000
b1111110101 3
b111111 6
b11111111101111110000 !
b11111111101111110000 .
b11111111101111110000 4
b111111 5
1'
b1111110101 (
b1111110101 -
b1011 ,
#6750000
0'
#7000000
b10010111 3
b111111 6
b11111111110110010010 !
b11111111110110010010 .
b11111111110110010010 4
b111111 5
1'
b10010111 (
b10010111 -
b1100 ,
#7250000
0'
#7500000
b1100111 3
b111111 6
b111110011 !
b111110011 .
b111110011 4
b111111 5
1'
b1100111 (
b1100111 -
b1101 ,
#7750000
0'
#8000000
b1100001011 3
b111111 6
b11011101011 !
b11011101011 .
b11011101011 4
b111111 5
1'
b1100001011 (
b1100001011 -
b1110 ,
#8250000
0'
#8500000
b1100000011 3
b111111 6
b110110001 !
b110110001 .
b110110001 4
b111111 5
1'
b1100000011 (
b1100000011 -
b1111 ,
#8750000
0'
#9000000
b11110111 3
b111111 6
b11111111011011011000 !
b11111111011011011000 .
b11111111011011011000 4
b111111 5
1'
b11110111 (
b11110111 -
b10000 ,
#9250000
0'
#9500000
b110010100 3
b111111 6
b11111111011010011100 !
b11111111011010011100 .
b11111111011010011100 4
b111111 5
1'
b110010100 (
b110010100 -
b10001 ,
#9750000
0'
#10000000
b1101100100 3
b111111 6
b10111101111 !
b10111101111 .
b10111101111 4
b111111 5
1'
b1101100100 (
b1101100100 -
b10010 ,
#10250000
0'
#10500000
b1000001110 3
b111111 6
b1000001101100 !
b1000001101100 .
b1000001101100 4
b111111 5
1'
b1000001110 (
b1000001110 -
b10011 ,
#10750000
0'
#11000000
b111 3
b111111 6
b110111100 !
b110111100 .
b110111100 4
b111111 5
1'
b111 (
b111 -
b10100 ,
#11250000
0'
#11500000
b111110100 3
b111111 6
b11111110101101010100 !
b11111110101101010100 .
b11111110101101010100 4
b111111 5
1'
b111110100 (
b111110100 -
b10101 ,
#11750000
0'
#12000000
b10001111 3
b111111 6
b11111111001010001011 !
b11111111001010001011 .
b11111111001010001011 4
b111111 5
1'
b10001111 (
b10001111 -
b10110 ,
#12250000
0'
#12500000
b1001100111 3
b111111 6
b1001011101100 !
b1001011101100 .
b1001011101100 4
b111111 5
1'
b1001100111 (
b1001100111 -
b10111 ,
#12750000
0'
#13000000
b1100010011 3
b111111 6
b1101101111000 !
b1101101111000 .
b1101101111000 4
b111111 5
1'
b1100010011 (
b1100010011 -
b11000 ,
#13250000
0'
#13500000
b100000011 3
b111111 6
b11111111011001011000 !
b11111111011001011000 .
b11111111011001011000 4
b111111 5
1'
b100000011 (
b100000011 -
b11001 ,
#13750000
0'
#14000000
b11101111 3
b111111 6
b11111101100000111111 !
b11111101100000111111 .
b11111101100000111111 4
b111111 5
1'
b11101111 (
b11101111 -
b11010 ,
#14250000
0'
#14500000
b1110010011 3
b111111 6
b11111111011111100100 !
b11111111011111100100 .
b11111111011111100100 4
b111111 5
1'
b1110010011 (
b1110010011 -
b11011 ,
#14750000
0'
#15000000
b1101101100 3
b111111 6
b11000011011100 !
b11000011011100 .
b11000011011100 4
b111111 5
1'
b1101101100 (
b1101101100 -
b11100 ,
#15250000
0'
#15500000
b1101 3
b111111 6
b10001111001010 !
b10001111001010 .
b10001111001010 4
b111111 5
1'
b1101 (
b1101 -
b11101 ,
#15750000
0'
#16000000
b1111111111 3
b111111 6
b11111100110110010110 !
b11111100110110010110 .
b11111100110110010110 4
b111111 5
1'
b1111111111 (
b1111111111 -
b11110 ,
#16250000
0'
#16500000
b1111110110 3
b111111 6
b11111010101110011011 !
b11111010101110011011 .
b11111010101110011011 4
b111111 5
1'
b1111110110 (
b1111110110 -
b11111 ,
#16750000
0'
#17000000
b10011000 3
b111111 6
b10011011010101 !
b10011011010101 .
b10011011010101 4
b111111 5
1'
b10011000 (
b10011000 -
b100000 ,
#17250000
0'
#17500000
b1100101 3
b111111 6
b1110010001011110 !
b1110010001011110 .
b1110010001011110 4
b111111 5
1'
b1100101 (
b1100101 -
b100001 ,
#17750000
0'
#18000000
b1100001000 3
b111111 6
b10000001001010101 !
b10000001001010101 .
b10000001001010101 4
b111111 5
1'
b1100001000 (
b1100001000 -
b100010 ,
#18250000
0'
#18500000
b1100000110 3
b111111 6
b11001110001101 !
b11001110001101 .
b11001110001101 4
b111111 5
1'
b1100000110 (
b1100000110 -
b100011 ,
#18750000
0'
#19000000
b11111100 3
b111111 6
b11110100010111011000 !
b11110100010111011000 .
b11110100010111011000 4
b111111 5
1'
b11111100 (
b11111100 -
b100100 ,
#19250000
0'
#19500000
b110010001 3
b111111 6
b11110100011101100101 !
b11110100011101100101 .
b11110100011101100101 4
b111111 5
1'
b110010001 (
b110010001 -
b100101 ,
#19750000
0'
#20000000
b1101011101 3
b111111 6
b11000010001010 !
b11000010001010 .
b11000010001010 4
b111111 5
1'
b1101011101 (
b1101011101 -
b100110 ,
#20250000
0'
#20500000
b1000001111 3
b111111 6
b1101010010011110 !
b1101010010011110 .
b1101010010011110 4
b111111 5
1'
b1000001111 (
b1000001111 -
b100111 ,
#20750000
0'
#21000000
b1110 3
b111111 6
b110000010101110 !
b110000010101110 .
b110000010101110 4
b111111 5
1'
b1110 (
b1110 -
b101000 ,
#21250000
0'
#21500000
b111110101 3
b111111 6
b11110110110100101110 !
b11110110110100101110 .
b11110110110100101110 4
b111111 5
1'
b111110101 (
b111110101 -
b101001 ,
#21750000
0'
#22000000
b10001000 3
b111111 6
b11110011111010001011 !
b11110011111010001011 .
b11110011111010001011 4
b111111 5
1'
b10001000 (
b10001000 -
b101010 ,
#22250000
0'
#22500000
b1001100101 3
b111111 6
b1010010100101 !
b1010010100101 .
b1010010100101 4
b111111 5
1'
b1001100101 (
b1001100101 -
b101011 ,
#22750000
0'
#23000000
b1100011000 3
b111111 6
b1101000011000111 !
b1101000011000111 .
b1101000011000111 4
b111111 5
1'
b1100011000 (
b1100011000 -
b101100 ,
#23250000
0'
#23500000
b100000111 3
b111111 6
b111001001000011 !
b111001001000011 .
b111001001000011 4
b111111 5
1'
b100000111 (
b100000111 -
b101101 ,
#23750000
0'
#24000000
b11101100 3
b111111 6
b11110111011011010110 !
b11110111011011010110 .
b11110111011011010110 4
b111111 5
1'
b11101100 (
b11101100 -
b101110 ,
#24250000
0'
#24500000
b1110010001 3
b111111 6
b11110011010001101101 !
b11110011010001101101 .
b11110011010001101101 4
b111111 5
1'
b1110010001 (
b1110010001 -
b101111 ,
#24750000
0'
#25000000
b1101101110 3
b111111 6
b100100011100 !
b100100011100 .
b100100011100 4
b111111 5
1'
b1101101110 (
b1101101110 -
b110000 ,
#25250000
0'
#25500000
b1110 3
b111111 6
b1101010000000101 !
b1101010000000101 .
b1101010000000101 4
b111111 5
1'
b1110 (
b1110 -
b110001 ,
#25750000
0'
#26000000
b1111111110 3
b111111 6
b111110001011100 !
b111110001011100 .
b111110001011100 4
b111111 5
1'
b1111111110 (
b1111111110 -
b110010 ,
#26250000
0'
#26500000
b1111110111 3
b111111 6
b11110111011101100100 !
b11110111011101100100 .
b11110111011101100100 4
b111111 5
1'
b1111110111 (
b1111110111 -
b110011 ,
#26750000
0'
#27000000
b10011010 3
b111111 6
b11110010110000101001 !
b11110010110000101001 .
b11110010110000101001 4
b111111 5
1'
b10011010 (
b10011010 -
b110100 ,
#27250000
0'
#27500000
b1100010 3
b111111 6
b10011000000 !
b10011000000 .
b10011000000 4
b111111 5
1'
b1100010 (
b1100010 -
b110101 ,
#27750000
0'
#28000000
b1100000101 3
b111111 6
b1101101000001100 !
b1101101000001100 .
b1101101000001100 4
b111111 5
1'
b1100000101 (
b1100000101 -
b110110 ,
#28250000
0'
#28500000
b1100001010 3
b111111 6
b1000000110110010 !
b1000000110110010 .
b1000000110110010 4
b111111 5
1'
b1100001010 (
b1100001010 -
b110111 ,
#28750000
0'
#29000000
b100000001 3
b111111 6
b11110111010010001111 !
b11110111010010001111 .
b11110111010010001111 4
b111111 5
1'
b100000001 (
b100000001 -
b111000 ,
#29250000
0'
#29500000
b110001110 3
b111111 6
b11110010100011010010 !
b11110010100011010010 .
b11110010100011010010 4
b111111 5
1'
b110001110 (
b110001110 -
b111001 ,
#29750000
0'
#30000000
b1101010111 3
b111111 6
b10111101110 !
b10111101110 .
b10111101110 4
b111111 5
1'
b1101010111 (
b1101010111 -
b111010 ,
#30250000
0'
#30500000
b1000010000 3
b111111 6
b1101101111100001 !
b1101101111100001 .
b1101101111100001 4
b111111 5
1'
b1000010000 (
b1000010000 -
b111011 ,
#30750000
0'
#31000000
b10101 3
b111111 6
b1000000101011100 !
b1000000101011100 .
b1000000101011100 4
b111111 5
1'
b10101 (
b10101 -
b111100 ,
#31250000
0'
#31500000
b111110110 3
b111111 6
b11110111001001001010 !
b11110111001001001010 .
b11110111001001001010 4
b111111 5
1'
b111110110 (
b111110110 -
b111101 ,
#31750000
0'
#32000000
b10000001 3
b111111 6
b11110010001111000001 !
b11110010001111000001 .
b11110010001111000001 4
b111111 5
1'
b10000001 (
b10000001 -
b111110 ,
#32250000
0'
#32500000
b1001100010 3
b111111 6
b10001110110 !
b10001110110 .
b10001110110 4
b111111 5
1'
b1001100010 (
b1001100010 -
b111111 ,
#32750000
0'
#33000000
b1100011101 3
b111111 6
b1101111100000111 !
b1101111100000111 .
b1101111100000111 4
b111111 5
1'
b1100011101 (
b1100011101 -
b1000000 ,
#33250000
0'
#33500000
b100001010 3
b111111 6
b1000010010011001 !
b1000010010011001 .
b1000010010011001 4
b111111 5
1'
b100001010 (
b100001010 -
b1000001 ,
#33750000
0'
#34000000
b11101001 3
b111111 6
b11110111001011100100 !
b11110111001011100100 .
b11110111001011100100 4
b111111 5
1'
b11101001 (
b11101001 -
b1000010 ,
#34250000
0'
#34500000
b1110001110 3
b111111 6
b11110010010100001101 !
b11110010010100001101 .
b11110010010100001101 4
b111111 5
1'
b1110001110 (
b1110001110 -
b1000011 ,
#34750000
0'
#35000000
b1101101111 3
b111111 6
b11000010010 !
b11000010010 .
b11000010010 4
b111111 5
1'
b1101101111 (
b1101101111 -
b1000100 ,
#35250000
0'
#35500000
b1111 3
b111111 6
b1101111000010000 !
b1101111000010000 .
b1101111000010000 4
b111111 5
1'
b1111 (
b1111 -
b1000101 ,
#35750000
0'
#36000000
b1111111110 3
b111111 6
b1000001011011000 !
b1000001011011000 .
b1000001011011000 4
b111111 5
1'
b1111111110 (
b1111111110 -
b1000110 ,
#36250000
0'
#36500000
b1111111000 3
b111111 6
b11110111001100010101 !
b11110111001100010101 .
b11110111001100010101 4
b111111 5
1'
b1111111000 (
b1111111000 -
b1000111 ,
#36750000
0'
#37000000
b10011011 3
b111111 6
b11110010010111110111 !
b11110010010111110111 .
b11110010010111110111 4
b111111 5
1'
b10011011 (
b10011011 -
b1001000 ,
#37250000
0'
#37500000
b1011111 3
b111111 6
b10110010000 !
b10110010000 .
b10110010000 4
b111111 5
1'
b1011111 (
b1011111 -
b1001001 ,
#37750000
0'
#38000000
b1100000010 3
b111111 6
b1101110101000011 !
b1101110101000011 .
b1101110101000011 4
b111111 5
1'
b1100000010 (
b1100000010 -
b1001010 ,
#38250000
0'
#38500000
b1100001101 3
b111111 6
b1000001101100011 !
b1000001101100011 .
b1000001101100011 4
b111111 5
1'
b1100001101 (
b1100001101 -
b1001011 ,
#38750000
0'
#39000000
b100000110 3
b111111 6
b11110111001111000010 !
b11110111001111000010 .
b11110111001111000010 4
b111111 5
1'
b100000110 (
b100000110 -
b1001100 ,
#39250000
0'
#39500000
b110001011 3
b111111 6
b11110010010110011100 !
b11110010010110011100 .
b11110010010110011100 4
b111111 5
1'
b110001011 (
b110001011 -
b1001101 ,
#39750000
0'
#40000000
b1101010000 3
b111111 6
b10111000000 !
b10111000000 .
b10111000000 4
b111111 5
1'
b1101010000 (
b1101010000 -
b1001110 ,
#40250000
0'
#40500000
b1000010010 3
b111111 6
b1101111011001011 !
b1101111011001011 .
b1101111011001011 4
b111111 5
1'
b1000010010 (
b1000010010 -
b1001111 ,
#40750000
0'
#41000000
b11100 3
b111111 6
b1000001111101001 !
b1000001111101001 .
b1000001111101001 4
b111111 5
1'
b11100 (
b11100 -
b1010000 ,
#41250000
0'
#41500000
b111110110 3
b111111 6
b11110111001000101111 !
b11110111001000101111 .
b11110111001000101111 4
b111111 5
1'
b111110110 (
b111110110 -
b1010001 ,
#41750000
0'
#42000000
b1111011 3
b111111 6
b11110010010011010101 !
b11110010010011010101 .
b11110010010011010101 4
b111111 5
1'
b1111011 (
b1111011 -
b1010010 ,
#42250000
0'
#42500000
b1001100000 3
b111111 6
b11101101011 !
b11101101011 .
b11101101011 4
b111111 5
1'
b1001100000 (
b1001100000 -
b1010011 ,
#42750000
0'
#43000000
b1100100010 3
b111111 6
b1101111111100101 !
b1101111111100101 .
b1101111111100101 4
b111111 5
1'
b1100100010 (
b1100100010 -
b1010100 ,
#43250000
0'
#43500000
b100001101 3
b111111 6
b1000001000111100 !
b1000001000111100 .
b1000001000111100 4
b111111 5
1'
b100001101 (
b100001101 -
b1010101 ,
#43750000
0'
#44000000
b11100110 3
b111111 6
b11110111000010101011 !
b11110111000010101011 .
b11110111000010101011 4
b111111 5
1'
b11100110 (
b11100110 -
b1010110 ,
#44250000
0'
#44500000
b1110001100 3
b111111 6
b11110010011000110010 !
b11110010011000110010 .
b11110010011000110010 4
b111111 5
1'
b1110001100 (
b1110001100 -
b1010111 ,
#44750000
0'
#45000000
b1101110000 3
b111111 6
b100100110010 !
b100100110010 .
b100100110010 4
b111111 5
1'
b1101110000 (
b1101110000 -
b1011000 ,
#45250000
0'
#45500000
b10000 3
b111111 6
b1101111100010011 !
b1101111100010011 .
b1101111100010011 4
b111111 5
1'
b10000 (
b10000 -
b1011001 ,
#45750000
0'
#46000000
b1111111101 3
b111111 6
b1000000010001011 !
b1000000010001011 .
b1000000010001011 4
b111111 5
1'
b1111111101 (
b1111111101 -
b1011010 ,
#46250000
0'
#46500000
b1111111001 3
b111111 6
b11110111000011010101 !
b11110111000011010101 .
b11110111000011010101 4
b111111 5
1'
b1111111001 (
b1111111001 -
b1011011 ,
#46750000
0'
#47000000
b10011100 3
b111111 6
b11110010011100000010 !
b11110010011100000010 .
b11110010011100000010 4
b111111 5
1'
b10011100 (
b10011100 -
b1011100 ,
#47250000
0'
#47500000
b1011100 3
b111111 6
b100001111011 !
b100001111011 .
b100001111011 4
b111111 5
1'
b1011100 (
b1011100 -
b1011101 ,
#47750000
0'
#48000000
b1011111111 3
b111111 6
b1101110111101011 !
b1101110111101011 .
b1101110111101011 4
b111111 5
1'
b1011111111 (
b1011111111 -
b1011110 ,
#48250000
0'
#48500000
b1100010000 3
b111111 6
b1000000010100111 !
b1000000010100111 .
b1000000010100111 4
b111111 5
1'
b1100010000 (
b1100010000 -
b1011111 ,
#48750000
0'
#49000000
b100001011 3
b111111 6
b11110111000100011110 !
b11110111000100011110 .
b11110111000100011110 4
b111111 5
1'
b100001011 (
b100001011 -
b1100000 ,
#49250000
0'
#49500000
b110001000 3
b111111 6
b11110010011001110000 !
b11110010011001110000 .
b11110010011001110000 4
b111111 5
1'
b110001000 (
b110001000 -
b1100001 ,
#49750000
0'
#50000000
b1101001010 3
b111111 6
b100010100001 !
b100010100001 .
b100010100001 4
b111111 5
1'
b1101001010 (
b1101001010 -
b1100010 ,
#50250000
0'
#50500000
b1000010011 3
b111111 6
b1101111101110101 !
b1101111101110101 .
b1101111101110101 4
b111111 5
1'
b1000010011 (
b1000010011 -
b1100011 ,
#50750000
0'
#51000000
b100100 3
b111111 6
b1000000100101000 !
b1000000100101000 .
b1000000100101000 4
b111111 5
1'
b100100 (
b100100 -
b1100100 ,
#51250000
0'
#51500000
b111110111 3
b111111 6
b11110110111110011101 !
b11110110111110011101 .
b11110110111110011101 4
b111111 5
1'
b111110111 (
b111110111 -
b1100101 ,
#51750000
0'
#52000000
b1110100 3
b111111 6
b11110010010111101000 !
b11110010010111101000 .
b11110010010111101000 4
b111111 5
1'
b1110100 (
b1110100 -
b1100110 ,
#52250000
0'
#52500000
b1001011110 3
b111111 6
b101010101100 !
b101010101100 .
b101010101100 4
b111111 5
1'
b1001011110 (
b1001011110 -
b1100111 ,
#52750000
0'
#53000000
b1100101000 3
b111111 6
b1110000011100110 !
b1110000011100110 .
b1110000011100110 4
b111111 5
1'
b1100101000 (
b1100101000 -
b1101000 ,
#53250000
0'
#53500000
b100010000 3
b111111 6
b111111110100110 !
b111111110100110 .
b111111110100110 4
b111111 5
1'
b100010000 (
b100010000 -
b1101001 ,
#53750000
0'
#54000000
b11100010 3
b111111 6
b11110110110111111101 !
b11110110110111111101 .
b11110110110111111101 4
b111111 5
1'
b11100010 (
b11100010 -
b1101010 ,
#54250000
0'
#54500000
b1110001010 3
b111111 6
b11110010011011011110 !
b11110010011011011110 .
b11110010011011011110 4
b111111 5
1'
b1110001010 (
b1110001010 -
b1101011 ,
#54750000
0'
#55000000
b1101110010 3
b111111 6
b101111110001 !
b101111110001 .
b101111110001 4
b111111 5
1'
b1101110010 (
b1101110010 -
b1101100 ,
#55250000
0'
#55500000
b10001 3
b111111 6
b1101111111001010 !
b1101111111001010 .
b1101111111001010 4
b111111 5
1'
b10001 (
b10001 -
b1101101 ,
#55750000
0'
#56000000
b1111111100 3
b111111 6
b111111000010010 !
b111111000010010 .
b111111000010010 4
b111111 5
1'
b1111111100 (
b1111111100 -
b1101110 ,
#56250000
0'
#56500000
b1111111010 3
b111111 6
b11110110111001111111 !
b11110110111001111111 .
b11110110111001111111 4
b111111 5
1'
b1111111010 (
b1111111010 -
b1101111 ,
#56750000
0'
#57000000
b10011110 3
b111111 6
b11110010011111110000 !
b11110010011111110000 .
b11110010011111110000 4
b111111 5
1'
b10011110 (
b10011110 -
b1110000 ,
#57250000
0'
#57500000
b1011010 3
b111111 6
b101101010110 !
b101101010110 .
b101101010110 4
b111111 5
1'
b1011010 (
b1011010 -
b1110001 ,
#57750000
0'
#58000000
b1011111100 3
b111111 6
b1101111010111100 !
b1101111010111100 .
b1101111010111100 4
b111111 5
1'
b1011111100 (
b1011111100 -
b1110010 ,
#58250000
0'
#58500000
b1100010100 3
b111111 6
b111111001010110 !
b111111001010110 .
b111111001010110 4
b111111 5
1'
b1100010100 (
b1100010100 -
b1110011 ,
#58750000
0'
#59000000
b100001111 3
b111111 6
b11110110111011111010 !
b11110110111011111010 .
b11110110111011111010 4
b111111 5
1'
b100001111 (
b100001111 -
b1110100 ,
#59250000
0'
#59500000
b110000101 3
b111111 6
b11110010011110010101 !
b11110010011110010101 .
b11110010011110010101 4
b111111 5
1'
b110000101 (
b110000101 -
b1110101 ,
#59750000
0'
#60000000
b1101000011 3
b111111 6
b101110100111 !
b101110100111 .
b101110100111 4
b111111 5
1'
b1101000011 (
b1101000011 -
b1110110 ,
#60250000
0'
#60500000
b1000010101 3
b111111 6
b1110000001010101 !
b1110000001010101 .
b1110000001010101 4
b111111 5
1'
b1000010101 (
b1000010101 -
b1110111 ,
#60750000
0'
#61000000
b101011 3
b111111 6
b111111011000111 !
b111111011000111 .
b111111011000111 4
b111111 5
1'
b101011 (
b101011 -
b1111000 ,
#61250000
0'
#61500000
b111110111 3
b111111 6
b11110110110101010011 !
b11110110110101010011 .
b11110110110101010011 4
b111111 5
1'
b111110111 (
b111110111 -
b1111001 ,
#61750000
0'
#62000000
b1101101 3
b111111 6
b11110010011011011010 !
b11110010011011011010 .
b11110010011011011010 4
b111111 5
1'
b1101101 (
b1101101 -
b1111010 ,
#62250000
0'
#62500000
b1001011100 3
b111111 6
b110101110010 !
b110101110010 .
b110101110010 4
b111111 5
1'
b1001011100 (
b1001011100 -
b1111011 ,
#62750000
0'
#63000000
b1100101101 3
b111111 6
b1110000101110111 !
b1110000101110111 .
b1110000101110111 4
b111111 5
1'
b1100101101 (
b1100101101 -
b1111100 ,
#63250000
0'
#63500000
b100010010 3
b111111 6
b111110011111110 !
b111110011111110 .
b111110011111110 4
b111111 5
1'
b100010010 (
b100010010 -
b1111101 ,
#63750000
0'
#64000000
b11011111 3
b111111 6
b11110110101101111110 !
b11110110101101111110 .
b11110110101101111110 4
b111111 5
1'
b11011111 (
b11011111 -
b1111110 ,
#64250000
0'
#64500000
b1110000111 3
b111111 6
b11110010011110101011 !
b11110010011110101011 .
b11110010011110101011 4
b111111 5
1'
b1110000111 (
b1110000111 -
b1111111 ,
#64750000
0'
#65000000
b1101110100 3
b111111 6
b111010100000 !
b111010100000 .
b111010100000 4
b111111 5
1'
b1101110100 (
b1101110100 -
b10000000 ,
#65250000
0'
#65500000
b10010 3
b111111 6
b1110000001110000 !
b1110000001110000 .
b1110000001110000 4
b111111 5
1'
b10010 (
b10010 -
b10000001 ,
#65750000
0'
#66000000
b1111111011 3
b111111 6
b111101110111100 !
b111101110111100 .
b111101110111100 4
b111111 5
1'
b1111111011 (
b1111111011 -
b10000010 ,
#66250000
0'
#66500000
b111111 6
b11110110110001111011 !
b11110110110001111011 .
b11110110110001111011 4
b111111 5
1'
b10000011 ,
#66750000
0'
#67000000
b10011111 3
b111111 6
b11110010100100111110 !
b11110010100100111110 .
b11110010100100111110 4
b111111 5
1'
b10011111 (
b10011111 -
b10000100 ,
#67250000
0'
#67500000
b1010111 3
b111111 6
b111001101100 !
b111001101100 .
b111001101100 4
b111111 5
1'
b1010111 (
b1010111 -
b10000101 ,
#67750000
0'
#68000000
b1011111010 3
b111111 6
b1101111110101111 !
b1101111110101111 .
b1101111110101111 4
b111111 5
1'
b1011111010 (
b1011111010 -
b10000110 ,
#68250000
0'
#68500000
b1100011000 3
b111111 6
b111110000110110 !
b111110000110110 .
b111110000110110 4
b111111 5
1'
b1100011000 (
b1100011000 -
b10000111 ,
#68750000
0'
#69000000
b100010100 3
b111111 6
b11110110110100010011 !
b11110110110100010011 .
b11110110110100010011 4
b111111 5
1'
b100010100 (
b100010100 -
b10001000 ,
#69250000
0'
#69500000
b110000010 3
b111111 6
b11110010100011010110 !
b11110010100011010110 .
b11110010100011010110 4
b111111 5
1'
b110000010 (
b110000010 -
b10001001 ,
#69750000
0'
#70000000
b1100111101 3
b111111 6
b111010001101 !
b111010001101 .
b111010001101 4
b111111 5
1'
b1100111101 (
b1100111101 -
b10001010 ,
#70250000
0'
#70500000
b1000010110 3
b111111 6
b1110000100000100 !
b1110000100000100 .
b1110000100000100 4
b111111 5
1'
b1000010110 (
b1000010110 -
b10001011 ,
#70750000
0'
#71000000
b110010 3
b111111 6
b111110001101010 !
b111110001101010 .
b111110001101010 4
b111111 5
1'
b110010 (
b110010 -
b10001100 ,
#71250000
0'
#71500000
b111110111 3
b111111 6
b11110110101101001101 !
b11110110101101001101 .
b11110110101101001101 4
b111111 5
1'
b111110111 (
b111110111 -
b10001101 ,
#71750000
0'
#72000000
b1100110 3
b111111 6
b11110010100000010011 !
b11110010100000010011 .
b11110010100000010011 4
b111111 5
1'
b1100110 (
b1100110 -
b10001110 ,
#72250000
0'
#72500000
b1001011010 3
b111111 6
b1000001010110 !
b1000001010110 .
b1000001010110 4
b111111 5
1'
b1001011010 (
b1001011010 -
b10001111 ,
#72750000
0'
#73000000
b1100110010 3
b111111 6
b1110001000111110 !
b1110001000111110 .
b1110001000111110 4
b111111 5
1'
b1100110010 (
b1100110010 -
b10010000 ,
#73250000
0'
#73500000
b100010101 3
b111111 6
b111101011101011 !
b111101011101011 .
b111101011101011 4
b111111 5
1'
b100010101 (
b100010101 -
b10010001 ,
#73750000
0'
#74000000
b11011100 3
b111111 6
b11110110100111100100 !
b11110110100111100100 .
b11110110100111100100 4
b111111 5
1'
b11011100 (
b11011100 -
b10010010 ,
